dictlistlib/__init__.py
dictlistlib/__main__.py
dictlistlib/application.py
dictlistlib/argumenthelper.py
dictlistlib/collection.py
dictlistlib/config.py
dictlistlib/constant.py
dictlistlib/dlquery.py
dictlistlib/exceptions.py
dictlistlib/factory.py
dictlistlib/main.py
dictlistlib/parser.py
dictlistlib/predicate.py
dictlistlib/tutorial.py
dictlistlib/utils.py
dictlistlib/validation.py
dictlistlib-0.4.1a1.dist-info/licenses/LICENSE
dictlistlib-0.4.1a1.dist-info/METADATA
dictlistlib-0.4.1a1.dist-info/WHEEL
dictlistlib-0.4.1a1.dist-info/entry_points.txt
dictlistlib-0.4.1a1.dist-info/top_level.txt
dictlistlib-0.4.1a1.dist-info/RECORD
