Metadata-Version: 2.4
Name: dictlistlib
Version: 0.4.1a1
Summary: dictlistlib simplifies querying Python dictionaries and lists with wildcards, regex, custom keywords, and SQL-like statements, streamlining data validation, filtering, and efficient workflows
Home-page: https://github.com/Geeks-Trident-LLC/dictlistlib
Author: Tuyen Mathew Duong
Author-email: tuyen@geekstrident.com
Maintainer: Tuyen Mathew Duong
Maintainer-email: tuyen@geekstrident.com
License: BSD-3-Clause
Project-URL: Documentation, https://github.com/Geeks-Trident-LLC/dictlistlib/wiki
Project-URL: Source, https://github.com/Geeks-Trident-LLC/dictlistlib
Project-URL: Tracker, https://github.com/Geeks-Trident-LLC/dictlistlib/issues
Keywords: dictionary,list,query,filter,automation,verification,testing,qa
Classifier: Development Status :: 3 - Alpha
Classifier: Natural Language :: English
Classifier: Intended Audience :: Developers
Classifier: Intended Audience :: Education
Classifier: Intended Audience :: End Users/Desktop
Classifier: Intended Audience :: Information Technology
Classifier: Intended Audience :: Manufacturing
Classifier: Intended Audience :: Other Audience
Classifier: Intended Audience :: Science/Research
Classifier: Operating System :: MacOS :: MacOS X
Classifier: Operating System :: POSIX :: Linux
Classifier: Operating System :: Microsoft :: Windows
Classifier: Programming Language :: Python
Classifier: Programming Language :: Python :: 3
Classifier: Programming Language :: Python :: 3.9
Classifier: Programming Language :: Python :: 3.10
Classifier: Programming Language :: Python :: 3.11
Classifier: Programming Language :: Python :: 3.12
Classifier: Topic :: Software Development :: Libraries :: Python Modules
Classifier: Topic :: Software Development :: Code Generators
Classifier: Topic :: Software Development :: Quality Assurance
Classifier: Topic :: Software Development :: Testing
Classifier: Topic :: Scientific/Engineering
Classifier: Topic :: Text Processing
License-File: LICENSE
Requires-Dist: compare_versions
Requires-Dist: python-dateutil
Requires-Dist: pyyaml
Dynamic: author
Dynamic: author-email
Dynamic: classifier
Dynamic: description
Dynamic: description-content-type
Dynamic: home-page
Dynamic: keywords
Dynamic: license
Dynamic: license-file
Dynamic: maintainer
Dynamic: maintainer-email
Dynamic: project-url
Dynamic: requires-dist
Dynamic: summary
